adafruit_tsl2591.py
adafruit_circuitpython_tsl2591-1.4.4.dist-info/licenses/LICENSE
adafruit_circuitpython_tsl2591-1.4.4.dist-info/METADATA
adafruit_circuitpython_tsl2591-1.4.4.dist-info/WHEEL
adafruit_circuitpython_tsl2591-1.4.4.dist-info/top_level.txt
adafruit_circuitpython_tsl2591-1.4.4.dist-info/RECORD
